examples/examples.py
opentts/__init__.py
opentts/client.py
opentts/providers/__init__.py
opentts/providers/_discovery.py
opentts/providers/provider_1/__init__.py
opentts/providers/provider_1/tts/__init__.py
opentts/providers/provider_1/tts/engine.py
opentts/providers/provider_2/__init__.py
opentts/providers/provider_2/tts/__init__.py
opentts/providers/provider_2/tts/engine.py
opentts/types/__init__.py
opentts/types/audio.py
opentts/types/chat.py
opentts_ai-0.1.1.dist-info/licenses/LICENSE
tests/test_tts.py
opentts_ai-0.1.1.dist-info/METADATA
opentts_ai-0.1.1.dist-info/WHEEL
opentts_ai-0.1.1.dist-info/top_level.txt
opentts_ai-0.1.1.dist-info/RECORD
